LICENSE
LICENSE.txt
MANIFEST.in
README.md
setup.py
bztt_fastapi_plus/__init__.py
bztt_fastapi_plus.egg-info/PKG-INFO
bztt_fastapi_plus.egg-info/SOURCES.txt
bztt_fastapi_plus.egg-info/dependency_links.txt
bztt_fastapi_plus.egg-info/requires.txt
bztt_fastapi_plus.egg-info/top_level.txt
bztt_fastapi_plus/config/__init__.py
bztt_fastapi_plus/config/anonymous.py
bztt_fastapi_plus/controller/__init__.py
bztt_fastapi_plus/controller/base.py
bztt_fastapi_plus/controller/demo.py
bztt_fastapi_plus/dao/__init__.py
bztt_fastapi_plus/dao/base.py
bztt_fastapi_plus/dao/demo.py
bztt_fastapi_plus/dao/event.py
bztt_fastapi_plus/dao/excel_base.py
bztt_fastapi_plus/model/__init__.py
bztt_fastapi_plus/model/base.py
bztt_fastapi_plus/model/base_excel.py
bztt_fastapi_plus/model/demo.py
bztt_fastapi_plus/model/event_log.py
bztt_fastapi_plus/schema/__init__.py
bztt_fastapi_plus/schema/base.py
bztt_fastapi_plus/schema/demo.py
bztt_fastapi_plus/service/__init__.py
bztt_fastapi_plus/service/base.py
bztt_fastapi_plus/service/base_un_log.py
bztt_fastapi_plus/service/demo.py
bztt_fastapi_plus/service/sys_info.py
bztt_fastapi_plus/utils/__init__.py
bztt_fastapi_plus/utils/auth.py
bztt_fastapi_plus/utils/custom_route.py
bztt_fastapi_plus/utils/db.py
bztt_fastapi_plus/utils/excel_db.py
bztt_fastapi_plus/utils/file_jwt.py
bztt_fastapi_plus/utils/generate_model.py
bztt_fastapi_plus/utils/json_custom.py
bztt_fastapi_plus/utils/json_encoders.py
bztt_fastapi_plus/utils/list2dict.py
bztt_fastapi_plus/utils/locker.py
bztt_fastapi_plus/utils/mongo.py
bztt_fastapi_plus/utils/my_jwt.py
bztt_fastapi_plus/utils/obj2dict.py
bztt_fastapi_plus/utils/obj2json.py
bztt_fastapi_plus/utils/re_error.py
bztt_fastapi_plus/utils/redis.py
bztt_fastapi_plus/utils/request_log.py
bztt_fastapi_plus/utils/sync_model.py
bztt_fastapi_plus/utils/wxapp.py